eikeskog_dev01/__init__.py
eikeskog_dev01/eikeskog.py
ste_ste_temp-0.0.4.dist-info/METADATA
ste_ste_temp-0.0.4.dist-info/WHEEL
ste_ste_temp-0.0.4.dist-info/top_level.txt
ste_ste_temp-0.0.4.dist-info/RECORD
