Metadata-Version: 2.1
Name: ste-ste-temp
Version: 0.0.4
Summary: Eikeskog test
Requires-Dist: certifi ==2023.11.17
Requires-Dist: charset-normalizer ==3.3.2
Requires-Dist: idna ==3.4
Requires-Dist: pip ==23.3.1
Requires-Dist: requests ==2.31.0
Requires-Dist: setuptools ==68.2.2
Requires-Dist: urllib3 ==2.1.0
Requires-Dist: wheel ==0.41.3
